pybot/__init__.py
pybot/bot.py
pybot/cli.py
pybot/management/__init__.py
pybot/management/builder.py
pybot/management/paraser.py
pybot/management/structure/__init__.py
pybot/management/structure/app.py
pybot/management/structure/main.py
pybot/management/structure/manage.py
pybot/management/structure/new_bot.py
pybot/management/structure/settings.py
socialpybot-0.0.1.dist-info/LICENCE
socialpybot-0.0.1.dist-info/METADATA
socialpybot-0.0.1.dist-info/WHEEL
socialpybot-0.0.1.dist-info/entry_points.txt
socialpybot-0.0.1.dist-info/top_level.txt
socialpybot-0.0.1.dist-info/RECORD
